google_play_scrapper/__init__.py
google_play_scrapper/exceptions.py
google_play_scrapper-0.0.1.dist-info/LICENSE
google_play_scrapper-0.0.1.dist-info/METADATA
google_play_scrapper-0.0.1.dist-info/WHEEL
google_play_scrapper-0.0.1.dist-info/top_level.txt
google_play_scrapper-0.0.1.dist-info/RECORD
