Metadata-Version: 2.1
Name: google-play-scrapper
Version: 0.0.1
Summary: This package is used to scrap data from google play for Feedbackio
Home-page: https://bitbucket.org/feedbackio1/google-play-scraper/src/master/
Author: Feedbackio
Author-email: dev@feedbackio.com
License: MIT
Keywords: python
Platform: UNKNOWN
Requires-Dist: tqdm (>=4.62.0)
